<?xml version="1.0" encoding="UTF-8"?>
<CompNfse xmlns="http://www.abrasf.org.br/nfse.xsd">
  <Nfse>
    <InfNfse>
      <Numero>1014</Numero>
      <DataEmissao>2026-05-15T10:30:00</DataEmissao>
      <PrestadorServico>
        <IdentificacaoPrestador>
          <Cnpj>67890123000145</Cnpj>
        </IdentificacaoPrestador>
        <RazaoSocial>Eventos Zeta Producoes Ltda</RazaoSocial>
      </PrestadorServico>
      <TomadorServico>
        <IdentificacaoTomador>
          <CpfCnpj><Cnpj>98765432000111</Cnpj></CpfCnpj>
        </IdentificacaoTomador>
      </TomadorServico>
      <ValoresNfse>
        <ValorLiquidoNfse>12400.00</ValorLiquidoNfse>
      </ValoresNfse>
    </InfNfse>
  </Nfse>
</CompNfse>
